NuPlone-4.0.3-py3.13-nspkg.pth
plonetheme/nuplone/__init__.py
plonetheme/nuplone/auth.py
plonetheme/nuplone/configure.zcml
plonetheme/nuplone/setuphandlers.py
plonetheme/nuplone/testing.py
plonetheme/nuplone/utils.py
plonetheme/nuplone/browser/__init__.py
plonetheme/nuplone/browser/configure.zcml
plonetheme/nuplone/browser/contact.py
plonetheme/nuplone/browser/helper.py
plonetheme/nuplone/browser/login.py
plonetheme/nuplone/browser/ordering.py
plonetheme/nuplone/browser/pwreminder.py
plonetheme/nuplone/browser/settings.py
plonetheme/nuplone/browser/wysiwyg.py
plonetheme/nuplone/browser/templates/editlink.pt
plonetheme/nuplone/browser/templates/login.pt
plonetheme/nuplone/browser/templates/pwreset-email.pt
plonetheme/nuplone/locales/nuplone.pot
plonetheme/nuplone/locales/bg/LC_MESSAGES/nuplone.po
plonetheme/nuplone/locales/ca/LC_MESSAGES/nuplone.po
plonetheme/nuplone/locales/cs/LC_MESSAGES/nuplone.po
plonetheme/nuplone/locales/de/LC_MESSAGES/nuplone.po
plonetheme/nuplone/locales/el/LC_MESSAGES/nuplone.po
plonetheme/nuplone/locales/es/LC_MESSAGES/nuplone.po
plonetheme/nuplone/locales/fi/LC_MESSAGES/nuplone.po
plonetheme/nuplone/locales/fr/LC_MESSAGES/nuplone.po
plonetheme/nuplone/locales/hr/LC_MESSAGES/nuplone.po
plonetheme/nuplone/locales/hu/LC_MESSAGES/nuplone.po
plonetheme/nuplone/locales/is/LC_MESSAGES/nuplone.po
plonetheme/nuplone/locales/it/LC_MESSAGES/nuplone.po
plonetheme/nuplone/locales/lt/LC_MESSAGES/nuplone.po
plonetheme/nuplone/locales/lv/LC_MESSAGES/nuplone.po
plonetheme/nuplone/locales/mt/LC_MESSAGES/nuplone.po
plonetheme/nuplone/locales/nl/LC_MESSAGES/nuplone.po
plonetheme/nuplone/locales/nl_BE/LC_MESSAGES/nuplone.po
plonetheme/nuplone/locales/pt/LC_MESSAGES/nuplone.po
plonetheme/nuplone/locales/sk/LC_MESSAGES/nuplone.po
plonetheme/nuplone/locales/sl/LC_MESSAGES/nuplone.po
plonetheme/nuplone/locales/sv/LC_MESSAGES/nuplone.po
plonetheme/nuplone/profiles/default/metadata.xml
plonetheme/nuplone/profiles/default/plonetheme.nuplone.txt
nuplone-4.0.3.dist-info/METADATA
nuplone-4.0.3.dist-info/WHEEL
nuplone-4.0.3.dist-info/namespace_packages.txt
nuplone-4.0.3.dist-info/top_level.txt
nuplone-4.0.3.dist-info/RECORD
