Metadata-Version: 2.4
Name: NuPlone
Version: 4.0.3
Summary: A new user interface for Plone
Home-page: https://github.com/euphorie/NuPlone
Author: Cornelis Kolbach, Wichert Akkerman and Syslab.com
Author-email: info@syslab.com
License: GPL
Keywords: web zope plone theme
Classifier: Development Status :: 5 - Production/Stable
Classifier: Environment :: Web Environment
Classifier: Framework :: Plone
Classifier: Framework :: Plone :: 6.0
Classifier: Framework :: Plone :: 6.1
Classifier: Framework :: Zope
Classifier: Framework :: Zope :: 4
Classifier: Framework :: Zope :: 5
Classifier: License :: OSI Approved :: GNU General Public License (GPL)
Classifier: Operating System :: OS Independent
Classifier: Programming Language :: JavaScript
Classifier: Programming Language :: Python
Classifier: Programming Language :: Python :: 3.9
Classifier: Programming Language :: Python :: 3.10
Classifier: Programming Language :: Python :: 3.11
Classifier: Programming Language :: Python :: 3.12
Classifier: Programming Language :: Python :: 3.13
Requires-Python: >=3.9
Requires-Dist: setuptools
Requires-Dist: Plone>=5.2
Requires-Dist: Products.statusmessages
Requires-Dist: plone.api
Requires-Dist: plone.app.z3cform
Requires-Dist: plone.autoform
Requires-Dist: plone.dexterity
Requires-Dist: plone.formwidget.namedfile
Requires-Dist: plone.i18n
Requires-Dist: plone.supermodel
Requires-Dist: plone.tiles
Requires-Dist: plone.z3cform
Requires-Dist: z3c.form[extra]
Requires-Dist: zope.i18n
Provides-Extra: tests
Requires-Dist: plone.app.robotframework; extra == "tests"
Requires-Dist: plone.app.testing; extra == "tests"
Requires-Dist: plone.testing; extra == "tests"
Dynamic: author
Dynamic: author-email
Dynamic: classifier
Dynamic: description
Dynamic: home-page
Dynamic: keywords
Dynamic: license
Dynamic: provides-extra
Dynamic: requires-dist
Dynamic: requires-python
Dynamic: summary
